peco/__init__.py
peco/const.py
peco/py.typed
peco-0.1.2.dist-info/LICENSE
peco-0.1.2.dist-info/METADATA
peco-0.1.2.dist-info/WHEEL
peco-0.1.2.dist-info/RECORD
