Metadata-Version: 2.3
Name: peco
Version: 0.1.2
Summary: A library for interacting with the PECO outage map to gain the numbers from it.
License: MIT
Author: IceBotYT
Author-email: icebotyt@outlook.com
Requires-Python: >=3.8.1,<4.0
Classifier: Development Status :: 4 - Beta
Classifier: Intended Audience :: Developers
Classifier: License :: OSI Approved :: MIT License
Classifier: Operating System :: OS Independent
Classifier: Programming Language :: Python
Classifier: Programming Language :: Python :: 3
Classifier: Programming Language :: Python :: 3.9
Classifier: Programming Language :: Python :: 3.10
Classifier: Programming Language :: Python :: 3.11
Classifier: Programming Language :: Python :: 3.12
Classifier: Programming Language :: Python :: 3.13
Classifier: Programming Language :: Python :: 3.8
Classifier: Topic :: Software Development :: Libraries :: Python Modules
Classifier: Typing :: Typed
Requires-Dist: aiohttp (>=3.9.5,<4.0.0)
Requires-Dist: pydantic (>=1.8,<3.0)
Project-URL: Documentation, https://IceBotYT.github.io/peco-outage-api
Project-URL: Homepage, https://IceBotYT.github.io/peco-outage-api
Project-URL: Repository, https://github.com/IceBotYT/peco-outage-api
